nonebot_plugin_update-0.1.4.dist-info/METADATA
nonebot_plugin_update-0.1.4.dist-info/WHEEL
nonebot_plugin_update-0.1.4.dist-info/entry_points.txt
nonebot_plugin_update-0.1.4.dist-info/licenses/LICENSE
nonebot_plugin_update/__init__.py
nonebot_plugin_update/check.py
nonebot_plugin_update/config.py
nonebot_plugin_update/model.py
nonebot_plugin_update/version.py
nonebot_plugin_update-0.1.4.dist-info/RECORD
