Metadata-Version: 2.1
Name: nonebot-plugin-update
Version: 0.1.4
Summary: 用于检测 Nonebot 插件更新的 Nonebot 插件
Author-Email: djkcyl <cyl@cyllive.cn>
License: MIT
Requires-Python: >=3.10
Requires-Dist: nonebot2[fastapi,httpx]>=2.2.1
Requires-Dist: nonebot-adapter-onebot>=2.4.3
Requires-Dist: nonebot-plugin-localstore>=0.6.0
Requires-Dist: packaging>=24.2
Requires-Dist: nonebot-plugin-apscheduler>=0.4.0
